{
  "0000": {
    "name": "Alabama",
    "group": "state",
    "type": "place"
  },
  "0001": {
    "name": "Alaska",
    "group": "state",
    "type": "place"
  },
  "0002": {
    "name": "Arizona",
    "group": "state",
    "type": "place"
  },
  "0003": {
    "name": "Arkansas",
    "group": "state",
    "type": "place"
  },
  "0004": {
    "name": "California",
    "group": "state",
    "type": "place"
  },
  "0005": {
    "name": "Sonny Perdue",
    "group": "cabinet",
    "type": "person"
  },
  "0006": {
    "name": "William Barr",
    "group": "cabinet",
    "type": "person"
  },
  "0007": {
    "name": "Lamar Alexander",
    "group": "congress",
    "type": "person"
  }
}